codes/__init__.py
codes/code.py
codes/generators.py
codes/sequences.py
codes/tests/__init__.py
codes/utils/__init__.py
codes/utils/definitions.py
codes/utils/functions.py
codes/utils/tests/__init__.py
codes/utils/tests/test_functions.py
synbio/__init__.py
synbio/biopython.py
synbio/centraldogma.py
synbio/libraries.py
synbio/polymers.py
synbio/utils.py
synbio/codes/__init__.py
synbio/codes/code.py
synbio/codes/generators.py
synbio/codes/utils/__init__.py
synbio/codes/utils/definitions.py
synbio/codes/utils/functions.py
tests/__init__.py
tests/test_Code.py
tests/utils/__init__.py
tests/utils/test_functions.py
synbio_jecalles-0.0.1.dist-info/LICENSE
synbio_jecalles-0.0.1.dist-info/METADATA
synbio_jecalles-0.0.1.dist-info/WHEEL
synbio_jecalles-0.0.1.dist-info/top_level.txt
synbio_jecalles-0.0.1.dist-info/RECORD
