Metadata-Version: 2.1
Name: synbio-jecalles
Version: 0.0.1
Summary: Tools for doing synthetic biology
Home-page: https://github.com/jecalles/synbio
Author: Jonathan Calles
Author-email: callesjonathan@gmail.com
License: MIT
Platform: UNKNOWN
Classifier: Programming Language :: Python :: 3
Classifier: Operating System :: OS Independent
Requires-Python: >3.8
